tifffile/__init__.py
tifffile/__main__.py
tifffile/_imagecodecs.py
tifffile/geodb.py
tifffile/lsm2bin.py
tifffile/numcodecs.py
tifffile/py.typed
tifffile/tiff2fsspec.py
tifffile/tiffcomment.py
tifffile/tifffile.py
tifffile-2024.9.20.dist-info/LICENSE
tifffile-2024.9.20.dist-info/METADATA
tifffile-2024.9.20.dist-info/WHEEL
tifffile-2024.9.20.dist-info/entry_points.txt
tifffile-2024.9.20.dist-info/top_level.txt
tifffile-2024.9.20.dist-info/RECORD
