Metadata-Version: 2.1
Name: tifffile
Version: 2024.9.20
Summary: Read and write TIFF files
Home-page: https://www.cgohlke.com
Author: Christoph Gohlke
Author-email: cgohlke@cgohlke.com
License: BSD
Project-URL: Bug Tracker, https://github.com/cgohlke/tifffile/issues
Project-URL: Source Code, https://github.com/cgohlke/tifffile
Platform: any
Classifier: Development Status :: 4 - Beta
Classifier: License :: OSI Approved :: BSD License
Classifier: Intended Audience :: Science/Research
Classifier: Intended Audience :: Developers
Classifier: Operating System :: OS Independent
Classifier: Programming Language :: Python :: 3 :: Only
Classifier: Programming Language :: Python :: 3.10
Classifier: Programming Language :: Python :: 3.11
Classifier: Programming Language :: Python :: 3.12
Classifier: Programming Language :: Python :: 3.13
Requires-Python: >=3.10
License-File: LICENSE
Requires-Dist: numpy
Provides-Extra: codecs
Requires-Dist: imagecodecs>=2023.8.12; extra == "codecs"
Provides-Extra: xml
Requires-Dist: defusedxml; extra == "xml"
Requires-Dist: lxml; extra == "xml"
Provides-Extra: zarr
Requires-Dist: zarr; extra == "zarr"
Requires-Dist: fsspec; extra == "zarr"
Provides-Extra: plot
Requires-Dist: matplotlib; extra == "plot"
Provides-Extra: all
Requires-Dist: imagecodecs>=2023.8.12; extra == "all"
Requires-Dist: matplotlib; extra == "all"
Requires-Dist: defusedxml; extra == "all"
Requires-Dist: lxml; extra == "all"
Requires-Dist: zarr; extra == "all"
Requires-Dist: fsspec; extra == "all"
Provides-Extra: test
Requires-Dist: pytest; extra == "test"
Requires-Dist: imagecodecs; extra == "test"
Requires-Dist: czifile; extra == "test"
Requires-Dist: cmapfile; extra == "test"
Requires-Dist: oiffile; extra == "test"
Requires-Dist: lfdfiles; extra == "test"
Requires-Dist: psdtags; extra == "test"
Requires-Dist: roifile; extra == "test"
Requires-Dist: lxml; extra == "test"
Requires-Dist: zarr; extra == "test"
Requires-Dist: dask; extra == "test"
Requires-Dist: xarray; extra == "test"
Requires-Dist: fsspec; extra == "test"
Requires-Dist: defusedxml; extra == "test"
Requires-Dist: ndtiff; extra == "test"
